teachers_gitlab/__init__.py
teachers_gitlab/main.py
teachers_gitlab/utils.py
teachers_gitlab-0.3.0.dist-info/LICENSE
teachers_gitlab-0.3.0.dist-info/METADATA
teachers_gitlab-0.3.0.dist-info/WHEEL
teachers_gitlab-0.3.0.dist-info/entry_points.txt
teachers_gitlab-0.3.0.dist-info/top_level.txt
teachers_gitlab-0.3.0.dist-info/RECORD
