Metadata-Version: 2.1
Name: teachers-gitlab
Version: 0.3.0
Summary: CLI for mass actions on GitLab
Author-email: Vojtech Horky <horky@d3s.mff.cuni.cz>
Keywords: teaching,gitlab
Classifier: License :: OSI Approved :: Apache Software License
Classifier: Intended Audience :: Education
Classifier: Intended Audience :: Developers
Classifier: Environment :: Console
Classifier: Topic :: Education
Classifier: Topic :: Software Development :: Version Control :: Git
Classifier: Topic :: Utilities
Requires-Python: >=3.8
License-File: LICENSE
Requires-Dist: dateparser >=1.1.0
Requires-Dist: python-gitlab >=3.6.0
